MANIFEST.in
license.txt
setup.cfg
setup.py
lighting_baseline/__init__.py
lighting_baseline/exclusions.py
lighting_baseline/lighting_baseline.py
lighting_baseline/series.py
lighting_baseline/utils.py
lighting_baseline.egg-info/PKG-INFO
lighting_baseline.egg-info/SOURCES.txt
lighting_baseline.egg-info/dependency_links.txt
lighting_baseline.egg-info/requires.txt
lighting_baseline.egg-info/top_level.txt
lighting_baseline/r/LightingSummary.R
tests/data/test_dr_days.csv
tests/data/test_kw.csv
tests/data/test_kw_small.csv
tests/data/test_tariff.csv
tests/data/test_temp.csv
tests/data/test_temp_small.csv