Metadata-Version: 1.0
Name: lighting-baseline
Version: 0.1.0
Summary: A set of tools for analyzing electric lighting load shapes.
Home-page: UNKNOWN
Author: Lawrence Berkeley National Laboratory
Author-email: UNKNOWN
License: revised BSD
Platform: UNKNOWN
